oem_framework/__init__.py
oem_framework/format.py
oem_framework/plugin.py
oem_framework/core/__init__.py
oem_framework/core/elapsed.py
oem_framework/core/helpers.py
oem_framework/models/__init__.py
oem_framework/models/collection.py
oem_framework/models/database.py
oem_framework/models/episode.py
oem_framework/models/index.py
oem_framework/models/item.py
oem_framework/models/metadata.py
oem_framework/models/movie.py
oem_framework/models/part.py
oem_framework/models/range.py
oem_framework/models/season.py
oem_framework/models/show.py
oem_framework/models/core/__init__.py
oem_framework/models/core/registry.py
oem_framework/models/core/base/__init__.py
oem_framework/models/core/base/mapping.py
oem_framework/models/core/base/media.py
oem_framework/models/core/base/model.py
oem_framework/models/core/mixins/__init__.py
oem_framework/models/core/mixins/names.py
oem_framework/storage/__init__.py
oem_framework/storage/collection.py
oem_framework/storage/database.py
oem_framework/storage/index.py
oem_framework/storage/item.py
oem_framework/storage/metadata.py
oem_framework/storage/provider.py
oem_framework/storage/core/__init__.py
oem_framework/storage/core/base.py
oem_framework-1.3.2.dist-info/DESCRIPTION.rst
oem_framework-1.3.2.dist-info/METADATA
oem_framework-1.3.2.dist-info/RECORD
oem_framework-1.3.2.dist-info/WHEEL
oem_framework-1.3.2.dist-info/metadata.json
oem_framework-1.3.2.dist-info/pbr.json
oem_framework-1.3.2.dist-info/top_level.txt
